[
  {
    "name": "saleConfigList",
    "source": "service",
    "type": "object",
    "requestType": "object",
    "filterParams": [
      {
        "attrId": "133593",
        "code": "header",
        "name": "请求头参数",
        "sort": {
          "isSort": true
        },
        "initialData": {
          "type": "static",
          "value": ""
        },
        "type": "object"
      },
      {
        "attrId": "6786983",
        "code": "path",
        "name": "请求路径参数",
        "sort": {
          "isSort": true
        },
        "initialData": {
          "type": "static",
          "value": ""
        },
        "type": "object"
      },
      {
        "attrId": "7376077",
        "code": "query",
        "name": "URL 参数",
        "sort": {
          "isSort": true
        },
        "initialData": {
          "type": "static",
          "value": ""
        },
        "type": "object"
      },
      {
        "attrId": "110724",
        "code": "body",
        "name": "请求体",
        "sort": {
          "isSort": true
        },
        "initialData": {
          "type": "static",
          "value": ""
        },
        "type": "object",
        "children": [
          {
            "attrId": "6752181",
            "code": "saleDesc",
            "name": "新增节点",
            "sort": {
              "isSort": true
            },
            "initialData": {
              "type": "static"
            },
            "type": "string"
          },
          {
            "attrId": "294087",
            "code": "saleCode",
            "name": "saleCode",
            "sort": {
              "isSort": true
            },
            "initialData": {
              "type": "static"
            },
            "type": "string"
          },
          {
            "attrId": "026035",
            "code": "pageSize",
            "name": "pageSize",
            "sort": {
              "isSort": true
            },
            "initialData": {
              "type": "static"
            },
            "type": "long"
          },
          {
            "attrId": "229813",
            "code": "pageNum",
            "name": "pageNum",
            "sort": {
              "isSort": true
            },
            "initialData": {
              "type": "static"
            },
            "type": "long"
          },
          {
            "attrId": "7771103",
            "code": "saleName",
            "name": "saleName",
            "sort": {
              "isSort": true
            },
            "initialData": {
              "type": "static"
            },
            "type": "string"
          },
          {
            "attrId": "610559",
            "code": "lanId",
            "name": "lanId",
            "sort": {
              "isSort": true
            },
            "initialData": {
              "type": "static"
            },
            "type": "string"
          },
          {
            "attrId": "855995",
            "code": "saleStatus",
            "name": "saleStatus",
            "sort": {
              "isSort": true
            },
            "initialData": {
              "type": "static"
            },
            "type": "string"
          }
        ]
      }
    ],
    "outParams": [
      {
        "attrId": "244151",
        "code": "resultCode",
        "name": "resultCode",
        "sort": {
          "isSort": true
        },
        "initialData": {
          "type": "static"
        },
        "type": "string"
      },
      {
        "attrId": "913402",
        "code": "resultMsgCode",
        "name": "resultMsgCode",
        "sort": {
          "isSort": true
        },
        "initialData": {
          "type": "static"
        },
        "type": "string"
      },
      {
        "attrId": "24856",
        "code": "resultMsg",
        "name": "resultMsg",
        "sort": {
          "isSort": true
        },
        "initialData": {
          "type": "static"
        },
        "type": "string"
      },
      {
        "attrId": "316638",
        "code": "resultData",
        "name": "resultData",
        "sort": {
          "isSort": true
        },
        "initialData": {
          "type": "static"
        },
        "type": "object",
        "children": [
          {
            "attrId": "303041",
            "code": "total",
            "name": "total",
            "sort": {
              "isSort": true
            },
            "initialData": {
              "type": "static"
            },
            "type": "long"
          },
          {
            "attrId": "046675",
            "code": "current",
            "name": "current",
            "sort": {
              "isSort": true
            },
            "initialData": {
              "type": "static"
            },
            "type": "long"
          },
          {
            "attrId": "0001063",
            "code": "hitCount",
            "name": "hitCount",
            "sort": {
              "isSort": true
            },
            "initialData": {
              "type": "static"
            },
            "type": "boolean"
          },
          {
            "attrId": "995593",
            "code": "size",
            "name": "size",
            "sort": {
              "isSort": true
            },
            "initialData": {
              "type": "static"
            },
            "type": "long"
          },
          {
            "attrId": "689062",
            "code": "optimizeCountSql",
            "name": "optimizeCountSql",
            "sort": {
              "isSort": true
            },
            "initialData": {
              "type": "static"
            },
            "type": "boolean"
          },
          {
            "attrId": "21058",
            "code": "maxLimit",
            "name": "maxLimit",
            "sort": {
              "isSort": true
            },
            "initialData": {
              "type": "static"
            },
            "type": "string"
          },
          {
            "attrId": "66088",
            "code": "orders",
            "name": "orders",
            "sort": {
              "isSort": true
            },
            "initialData": {
              "type": "static"
            },
            "type": "fieldArray",
            "children": [
              {
                "attrId": "0804708",
                "code": "listItem",
                "name": "列表元素",
                "sort": {
                  "isSort": true
                },
                "initialData": {
                  "type": "static"
                },
                "type": "object"
              }
            ]
          },
          {
            "attrId": "325067",
            "code": "countId",
            "name": "countId",
            "sort": {
              "isSort": true
            },
            "initialData": {
              "type": "static"
            },
            "type": "string"
          },
          {
            "attrId": "345559",
            "code": "isSearchCount",
            "name": "isSearchCount",
            "sort": {
              "isSort": true
            },
            "initialData": {
              "type": "static"
            },
            "type": "boolean"
          },
          {
            "attrId": "268765",
            "code": "records",
            "name": "records",
            "sort": {
              "isSort": true
            },
            "initialData": {
              "type": "static"
            },
            "type": "objectArray",
            "children": [
              {
                "attrId": "0922778",
                "code": "saleCfgId",
                "name": "saleCfgId",
                "sort": {
                  "isSort": true
                },
                "initialData": {
                  "type": "static"
                },
                "type": "long"
              },
              {
                "attrId": "673411",
                "code": "createDate",
                "name": "createDate",
                "sort": {
                  "isSort": true
                },
                "initialData": {
                  "type": "static"
                },
                "type": "string"
              },
              {
                "attrId": "375784",
                "code": "updateStaff",
                "name": "updateStaff",
                "sort": {
                  "isSort": true
                },
                "initialData": {
                  "type": "static"
                },
                "type": "string"
              },
              {
                "attrId": "524284",
                "code": "updateDate",
                "name": "updateDate",
                "sort": {
                  "isSort": true
                },
                "initialData": {
                  "type": "static"
                },
                "type": "string"
              },
              {
                "attrId": "5733842",
                "code": "saleDesc",
                "name": "saleDesc",
                "sort": {
                  "isSort": true
                },
                "initialData": {
                  "type": "static"
                },
                "type": "string"
              },
              {
                "attrId": "31721",
                "code": "saleCode",
                "name": "saleCode",
                "sort": {
                  "isSort": true
                },
                "initialData": {
                  "type": "static"
                },
                "type": "string"
              },
              {
                "attrId": "3398665",
                "code": "statusCd",
                "name": "statusCd",
                "sort": {
                  "isSort": true
                },
                "initialData": {
                  "type": "static"
                },
                "type": "string"
              },
              {
                "attrId": "68041",
                "code": "remark",
                "name": "remark",
                "sort": {
                  "isSort": true
                },
                "initialData": {
                  "type": "static"
                },
                "type": "string"
              },
              {
                "attrId": "425197",
                "code": "lanId",
                "name": "lanId",
                "sort": {
                  "isSort": true
                },
                "initialData": {
                  "type": "static"
                },
                "type": "string"
              },
              {
                "attrId": "766733",
                "code": "saleStatus",
                "name": "saleStatus",
                "sort": {
                  "isSort": true
                },
                "initialData": {
                  "type": "static"
                },
                "type": "string"
              },
              {
                "attrId": "439669",
                "code": "createStaff",
                "name": "createStaff",
                "sort": {
                  "isSort": true
                },
                "initialData": {
                  "type": "static"
                },
                "type": "string"
              },
              {
                "attrId": "0581602",
                "code": "createStaffName",
                "name": "createStaffName",
                "sort": {
                  "isSort": true
                },
                "initialData": {
                  "type": "static"
                },
                "type": "string"
              },
              {
                "attrId": "59881795",
                "code": "saleName",
                "name": "saleName",
                "sort": {
                  "isSort": true
                },
                "initialData": {
                  "type": "static"
                },
                "type": "string"
              }
            ]
          }
        ]
      }
    ],
    "config": {
      "hooks": [],
      "isInit": false,
      "options": {
        "service": {
          "busiApiId": "912648695968444416",
          "busiApiNbr": "qrySaleConfigPage",
          "busiApiName": "根据查询条件分页查询营销案列表-tsm",
          "busiObjId": "912648695968444416",
          "apiParam": "[{\"apiId\":912648695968444416,\"apiParamId\":912648695993610240,\"compareFlag\":true,\"createDate\":1669198805280,\"createStaff\":21826,\"objId\":912648695968444416,\"objType\":\"5000\",\"paramObject\":{\"compareFlag\":true,\"createDate\":1669198805280,\"createStaff\":21826,\"isList\":\"F\",\"level\":1,\"parServiceObjectId\":-1,\"paramType\":\"1000\",\"remark\":\"根节点，这个节点不能删除\",\"rootServiceObjectId\":912648695993610241,\"serviceObject\":[],\"serviceObjectCode\":\"root\",\"serviceObjectId\":912648695993610241,\"serviceObjectPath\":\"912648695993610241\",\"statusCd\":\"1000\",\"statusDate\":1669258276754,\"tenantCode\":\"868768414651416576\"},\"paramObjectId\":912648695993610241,\"paramType\":\"1000\",\"statusCd\":\"1000\",\"statusDate\":1669198805280,\"tenantCode\":\"868768414651416576\"},{\"apiId\":912648695968444416,\"apiParamId\":912648695997804544,\"compareFlag\":true,\"createDate\":1669198805280,\"createStaff\":21826,\"objId\":912648695968444416,\"objType\":\"5000\",\"paramObject\":{\"compareFlag\":true,\"createDate\":1669198805280,\"createStaff\":21826,\"isList\":\"F\",\"level\":1,\"parServiceObjectId\":-1,\"paramType\":\"2000\",\"remark\":\"根节点，这个节点不能删除\",\"rootServiceObjectId\":912648695997804545,\"serviceObject\":[],\"serviceObjectCode\":\"root\",\"serviceObjectId\":912648695997804545,\"serviceObjectPath\":\"912648695997804545\",\"statusCd\":\"1000\",\"statusDate\":1669258276754,\"tenantCode\":\"868768414651416576\"},\"paramObjectId\":912648695997804545,\"paramType\":\"2000\",\"statusCd\":\"1000\",\"statusDate\":1669198805280,\"tenantCode\":\"868768414651416576\"},{\"apiId\":912648695968444416,\"apiParamId\":912648695997804546,\"compareFlag\":true,\"createDate\":1669198805280,\"createStaff\":21826,\"objId\":912648695968444416,\"objType\":\"5000\",\"paramObject\":{\"compareFlag\":true,\"createDate\":1669198805280,\"createStaff\":21826,\"isList\":\"F\",\"level\":1,\"parServiceObjectId\":-1,\"paramType\":\"3000\",\"remark\":\"根节点，这个节点不能删除\",\"rootServiceObjectId\":912648695997804547,\"serviceObject\":[],\"serviceObjectCode\":\"root\",\"serviceObjectId\":912648695997804547,\"serviceObjectPath\":\"912648695997804547\",\"statusCd\":\"1000\",\"statusDate\":1669258276754,\"tenantCode\":\"868768414651416576\"},\"paramObjectId\":912648695997804547,\"paramType\":\"3000\",\"statusCd\":\"1000\",\"statusDate\":1669198805280,\"tenantCode\":\"868768414651416576\"},{\"apiId\":912648695968444416,\"apiParamId\":912648695997804548,\"compareFlag\":true,\"createDate\":1669198805280,\"createStaff\":21826,\"objId\":912648695968444416,\"objType\":\"5000\",\"paramObject\":{\"compareFlag\":true,\"createDate\":1669198805280,\"createStaff\":21826,\"isList\":\"F\",\"level\":1,\"parServiceObjectId\":-1,\"paramType\":\"4000\",\"remark\":\"根节点\",\"rootServiceObjectId\":912648695997804549,\"serviceObject\":[],\"serviceObjectAttrs\":[{\"attrId\":907509970332381188,\"attrSpec\":{\"attrId\":907509970332381188,\"attrName\":\"saleDesc\",\"attrNbr\":\"saleDesc\",\"attrValueDataType\":\"1200\",\"busiTypeId\":1,\"statusCd\":\"1000\"},\"compareFlag\":true,\"createDate\":1669258276754,\"createStaff\":21826,\"defaultValue\":\"\",\"desensitizeRule\":\"1001\",\"desensitizeType\":\"1001\",\"exampleValue\":\"\",\"mustFlag\":\"F\",\"remark\":\"新增节点\",\"serviceObjAttrId\":912898138449915904,\"serviceObjectId\":912648695997804549,\"statusCd\":\"1000\",\"statusDate\":1669258276754,\"tenantCode\":\"868768414651416576\"},{\"attrId\":912648696073302017,\"attrSpec\":{\"attrId\":912648696073302017,\"attrName\":\"saleCode\",\"attrNbr\":\"saleCode\",\"attrValueDataType\":\"1200\",\"busiTypeId\":1,\"statusCd\":\"1000\"},\"compareFlag\":true,\"createDate\":1669198805280,\"createStaff\":21826,\"exampleValue\":\"\",\"mustFlag\":\"F\",\"serviceObjAttrId\":912648696073302016,\"serviceObjectId\":912648695997804549,\"statusCd\":\"1000\",\"statusDate\":1669258276754,\"tenantCode\":\"868768414651416576\"},{\"attrId\":844138525246029829,\"attrSpec\":{\"attrId\":844138525246029829,\"attrName\":\"pageSize\",\"attrNbr\":\"pageSize\",\"attrValueDataType\":\"1400\",\"busiTypeId\":1,\"statusCd\":\"1000\"},\"compareFlag\":true,\"createDate\":1669198805280,\"createStaff\":21826,\"exampleValue\":\"5\",\"mustFlag\":\"F\",\"serviceObjAttrId\":912648696077496323,\"serviceObjectId\":912648695997804549,\"statusCd\":\"1000\",\"statusDate\":1669258276754,\"tenantCode\":\"868768414651416576\"},{\"attrId\":844138523346010119,\"attrSpec\":{\"attrId\":844138523346010119,\"attrName\":\"pageNum\",\"attrNbr\":\"pageNum\",\"attrValueDataType\":\"1400\",\"busiTypeId\":1,\"statusCd\":\"1000\"},\"compareFlag\":true,\"createDate\":1669198805280,\"createStaff\":21826,\"exampleValue\":\"1\",\"mustFlag\":\"F\",\"serviceObjAttrId\":912648696077496322,\"serviceObjectId\":912648695997804549,\"statusCd\":\"1000\",\"statusDate\":1669258276754,\"tenantCode\":\"868768414651416576\"},{\"attrId\":907469056321548290,\"attrSpec\":{\"attrId\":907469056321548290,\"attrName\":\"saleName\",\"attrNbr\":\"saleName\",\"attrValueDataType\":\"1200\",\"busiTypeId\":1,\"statusCd\":\"1000\"},\"compareFlag\":true,\"createDate\":1669198805280,\"createStaff\":21826,\"exampleValue\":\"\",\"mustFlag\":\"F\",\"serviceObjAttrId\":912648696073302018,\"serviceObjectId\":912648695997804549,\"statusCd\":\"1000\",\"statusDate\":1669258276754,\"tenantCode\":\"868768414651416576\"},{\"attrId\":854315411091636226,\"attrSpec\":{\"attrId\":854315411091636226,\"attrName\":\"lanId\",\"attrNbr\":\"lanId\",\"attrValueDataType\":\"1200\",\"busiTypeId\":1,\"statusCd\":\"1000\"},\"compareFlag\":true,\"createDate\":1669198805280,\"createStaff\":21826,\"exampleValue\":\"\",\"mustFlag\":\"F\",\"serviceObjAttrId\":912648696073302019,\"serviceObjectId\":912648695997804549,\"statusCd\":\"1000\",\"statusDate\":1669258276754,\"tenantCode\":\"868768414651416576\"},{\"attrId\":912648696077496321,\"attrSpec\":{\"attrId\":912648696077496321,\"attrName\":\"saleStatus\",\"attrNbr\":\"saleStatus\",\"attrValueDataType\":\"1200\",\"busiTypeId\":1,\"statusCd\":\"1000\"},\"compareFlag\":true,\"createDate\":1669198805280,\"createStaff\":21826,\"exampleValue\":\"\",\"mustFlag\":\"F\",\"serviceObjAttrId\":912648696077496320,\"serviceObjectId\":912648695997804549,\"statusCd\":\"1000\",\"statusDate\":1669258276754,\"tenantCode\":\"868768414651416576\"}],\"serviceObjectCode\":\"root\",\"serviceObjectId\":912648695997804549,\"serviceObjectPath\":\"912648695997804549\",\"statusCd\":\"1000\",\"statusDate\":1669258276754,\"tenantCode\":\"868768414651416576\"},\"paramObjectId\":912648695997804549,\"paramType\":\"4000\",\"statusCd\":\"1000\",\"statusDate\":1669198805280,\"tenantCode\":\"868768414651416576\"},{\"apiId\":912648695968444416,\"apiParamId\":912648695997804550,\"compareFlag\":true,\"createDate\":1669198805280,\"createStaff\":21826,\"objId\":912648695968444416,\"objType\":\"5000\",\"paramObject\":{\"compareFlag\":true,\"createDate\":1669198805280,\"createStaff\":21826,\"isList\":\"F\",\"level\":1,\"parServiceObjectId\":-1,\"paramType\":\"5000\",\"remark\":\"根节点\",\"rootServiceObjectId\":912648695997804551,\"serviceObject\":[{\"compareFlag\":true,\"createDate\":1669198805280,\"createStaff\":21826,\"isList\":\"F\",\"level\":2,\"parServiceObjectId\":912648695997804551,\"paramType\":\"5000\",\"rootServiceObjectId\":912648695997804551,\"serviceObject\":[{\"compareFlag\":true,\"createDate\":1669198805280,\"createStaff\":21826,\"isList\":\"T\",\"level\":3,\"parServiceObjectId\":912648696119439360,\"paramType\":\"5000\",\"rootServiceObjectId\":912648695997804551,\"serviceObject\":[],\"serviceObjectAttrs\":[{\"attrId\":912648696207519746,\"attrSpec\":{\"attrId\":912648696207519746,\"attrName\":\"saleCfgId\",\"attrNbr\":\"saleCfgId\",\"attrValueDataType\":\"1400\",\"busiTypeId\":1,\"statusCd\":\"1000\"},\"compareFlag\":true,\"createDate\":1669198805280,\"createStaff\":21826,\"exampleValue\":\"1\",\"mustFlag\":\"F\",\"serviceObjAttrId\":912648696207519745,\"serviceObjectId\":912648696119439361,\"statusCd\":\"1000\",\"statusDate\":1669258276754,\"tenantCode\":\"868768414651416576\"},{\"attrId\":1127806,\"attrSpec\":{\"attrId\":1127806,\"attrName\":\"createDate\",\"attrNbr\":\"createDate\",\"attrValueDataType\":\"1200\",\"busiTypeId\":1,\"statusCd\":\"1000\"},\"compareFlag\":true,\"createDate\":1669198805280,\"createStaff\":21826,\"exampleValue\":\"2022-11-2317:55:47\",\"mustFlag\":\"F\",\"serviceObjAttrId\":912648696207519747,\"serviceObjectId\":912648696119439361,\"statusCd\":\"1000\",\"statusDate\":1669258276754,\"tenantCode\":\"868768414651416576\"},{\"attrId\":1127805,\"attrSpec\":{\"attrId\":1127805,\"attrName\":\"updateStaff\",\"attrNbr\":\"updateStaff\",\"attrValueDataType\":\"1200\",\"busiTypeId\":1,\"statusCd\":\"1000\"},\"compareFlag\":true,\"createDate\":1669198805280,\"createStaff\":21826,\"mustFlag\":\"F\",\"serviceObjAttrId\":912648696211714048,\"serviceObjectId\":912648696119439361,\"statusCd\":\"1000\",\"statusDate\":1669258276754,\"tenantCode\":\"868768414651416576\"},{\"attrId\":1127807,\"attrSpec\":{\"attrId\":1127807,\"attrName\":\"updateDate\",\"attrNbr\":\"updateDate\",\"attrValueDataType\":\"1200\",\"busiTypeId\":1,\"statusCd\":\"1000\"},\"compareFlag\":true,\"createDate\":1669198805280,\"createStaff\":21826,\"mustFlag\":\"F\",\"serviceObjAttrId\":912648696203325440,\"serviceObjectId\":912648696119439361,\"statusCd\":\"1000\",\"statusDate\":1669258276754,\"tenantCode\":\"868768414651416576\"},{\"attrId\":907509970332381188,\"attrSpec\":{\"attrId\":907509970332381188,\"attrName\":\"saleDesc\",\"attrNbr\":\"saleDesc\",\"attrValueDataType\":\"1200\",\"busiTypeId\":1,\"statusCd\":\"1000\"},\"compareFlag\":true,\"createDate\":1669198805280,\"createStaff\":21826,\"exampleValue\":\"营销案A\",\"mustFlag\":\"F\",\"serviceObjAttrId\":912648696203325441,\"serviceObjectId\":912648696119439361,\"statusCd\":\"1000\",\"statusDate\":1669258276754,\"tenantCode\":\"868768414651416576\"},{\"attrId\":912648696203325443,\"attrSpec\":{\"attrId\":912648696203325443,\"attrName\":\"saleCode\",\"attrNbr\":\"saleCode\",\"attrValueDataType\":\"1200\",\"busiTypeId\":1,\"statusCd\":\"1000\"},\"compareFlag\":true,\"createDate\":1669198805280,\"createStaff\":21826,\"exampleValue\":\"营销案A\",\"mustFlag\":\"F\",\"serviceObjAttrId\":912648696203325442,\"serviceObjectId\":912648696119439361,\"statusCd\":\"1000\",\"statusDate\":1669258276754,\"tenantCode\":\"868768414651416576\"},{\"attrId\":848827256929415168,\"attrSpec\":{\"attrId\":848827256929415168,\"attrName\":\"statusCd\",\"attrNbr\":\"statusCd\",\"attrValueDataType\":\"1200\",\"busiTypeId\":1,\"statusCd\":\"1000\"},\"compareFlag\":true,\"createDate\":1669198805280,\"createStaff\":21826,\"exampleValue\":\"00A\",\"mustFlag\":\"F\",\"serviceObjAttrId\":912648696203325444,\"serviceObjectId\":912648696119439361,\"statusCd\":\"1000\",\"statusDate\":1669258276754,\"tenantCode\":\"868768414651416576\"},{\"attrId\":848827256916832256,\"attrSpec\":{\"attrId\":848827256916832256,\"attrName\":\"remark\",\"attrNbr\":\"remark\",\"attrValueDataType\":\"1200\",\"busiTypeId\":1,\"statusCd\":\"1000\"},\"compareFlag\":true,\"createDate\":1669198805280,\"createStaff\":21826,\"mustFlag\":\"F\",\"serviceObjAttrId\":912648696203325445,\"serviceObjectId\":912648696119439361,\"statusCd\":\"1000\",\"statusDate\":1669258276754,\"tenantCode\":\"868768414651416576\"},{\"attrId\":854315411091636226,\"attrSpec\":{\"attrId\":854315411091636226,\"attrName\":\"lanId\",\"attrNbr\":\"lanId\",\"attrValueDataType\":\"1200\",\"busiTypeId\":1,\"statusCd\":\"1000\"},\"compareFlag\":true,\"createDate\":1669198805280,\"createStaff\":21826,\"exampleValue\":\"3501\",\"mustFlag\":\"F\",\"serviceObjAttrId\":912648696203325446,\"serviceObjectId\":912648696119439361,\"statusCd\":\"1000\",\"statusDate\":1669258276754,\"tenantCode\":\"868768414651416576\"},{\"attrId\":912648696203325448,\"attrSpec\":{\"attrId\":912648696203325448,\"attrName\":\"saleStatus\",\"attrNbr\":\"saleStatus\",\"attrValueDataType\":\"1200\",\"busiTypeId\":1,\"statusCd\":\"1000\"},\"compareFlag\":true,\"createDate\":1669198805280,\"createStaff\":21826,\"exampleValue\":\"1000\",\"mustFlag\":\"F\",\"serviceObjAttrId\":912648696203325447,\"serviceObjectId\":912648696119439361,\"statusCd\":\"1000\",\"statusDate\":1669258276754,\"tenantCode\":\"868768414651416576\"},{\"attrId\":1130511,\"attrSpec\":{\"attrId\":1130511,\"attrNbr\":\"createStaff\",\"attrValueDataType\":\"1200\",\"busiTypeId\":1,\"statusCd\":\"1000\"},\"compareFlag\":true,\"createDate\":1669198805280,\"createStaff\":21826,\"exampleValue\":\"admin\",\"mustFlag\":\"F\",\"serviceObjAttrId\":912648696203325449,\"serviceObjectId\":912648696119439361,\"statusCd\":\"1000\",\"statusDate\":1669258276754,\"tenantCode\":\"868768414651416576\"},{\"attrId\":4254,\"attrSpec\":{\"attrId\":4254,\"attrName\":\"createStaffName\",\"attrNbr\":\"createStaffName\",\"attrValueDataType\":\"1200\",\"busiTypeId\":1,\"statusCd\":\"1000\"},\"compareFlag\":true,\"createDate\":1669198805280,\"createStaff\":21826,\"exampleValue\":\"管理员\",\"mustFlag\":\"F\",\"serviceObjAttrId\":912648696203325450,\"serviceObjectId\":912648696119439361,\"statusCd\":\"1000\",\"statusDate\":1669258276754,\"tenantCode\":\"868768414651416576\"},{\"attrId\":907469056321548290,\"attrSpec\":{\"attrId\":907469056321548290,\"attrName\":\"saleName\",\"attrNbr\":\"saleName\",\"attrValueDataType\":\"1200\",\"busiTypeId\":1,\"statusCd\":\"1000\"},\"compareFlag\":true,\"createDate\":1669198805280,\"createStaff\":21826,\"exampleValue\":\"营销案A\",\"mustFlag\":\"F\",\"serviceObjAttrId\":912648696207519744,\"serviceObjectId\":912648696119439361,\"statusCd\":\"1000\",\"statusDate\":1669258276754,\"tenantCode\":\"868768414651416576\"}],\"serviceObjectCode\":\"records\",\"serviceObjectId\":912648696119439361,\"serviceObjectPath\":\"912648695997804551,912648696119439360,912648696119439361\",\"statusCd\":\"1000\",\"statusDate\":1669258276754,\"tenantCode\":\"868768414651416576\"}],\"serviceObjectAttrs\":[{\"attrId\":844138525246029825,\"attrSpec\":{\"attrId\":844138525246029825,\"attrName\":\"total\",\"attrNbr\":\"total\",\"attrValueDataType\":\"1400\",\"busiTypeId\":1,\"statusCd\":\"1000\"},\"compareFlag\":true,\"createDate\":1669198805280,\"createStaff\":21826,\"exampleValue\":\"1\",\"mustFlag\":\"F\",\"serviceObjAttrId\":912648696161382400,\"serviceObjectId\":912648696119439360,\"statusCd\":\"1000\",\"statusDate\":1669258276754,\"tenantCode\":\"868768414651416576\"},{\"attrId\":3942,\"attrSpec\":{\"attrId\":3942,\"attrName\":\"current\",\"attrNbr\":\"current\",\"attrValueDataType\":\"1400\",\"busiTypeId\":1,\"statusCd\":\"1000\"},\"compareFlag\":true,\"createDate\":1669198805280,\"createStaff\":21826,\"exampleValue\":\"1\",\"mustFlag\":\"F\",\"serviceObjAttrId\":912648696161382401,\"serviceObjectId\":912648696119439360,\"statusCd\":\"1000\",\"statusDate\":1669258276754,\"tenantCode\":\"868768414651416576\"},{\"attrId\":3943,\"attrSpec\":{\"attrId\":3943,\"attrName\":\"hitCount\",\"attrNbr\":\"hitCount\",\"attrValueDataType\":\"1500\",\"busiTypeId\":1,\"statusCd\":\"1000\"},\"compareFlag\":true,\"createDate\":1669198805280,\"createStaff\":21826,\"exampleValue\":\"false\",\"mustFlag\":\"F\",\"serviceObjAttrId\":912648696161382402,\"serviceObjectId\":912648696119439360,\"statusCd\":\"1000\",\"statusDate\":1669258276754,\"tenantCode\":\"868768414651416576\"},{\"attrId\":844138525246029831,\"attrSpec\":{\"attrId\":844138525246029831,\"attrName\":\"size\",\"attrNbr\":\"size\",\"attrValueDataType\":\"1400\",\"busiTypeId\":1,\"statusCd\":\"1000\"},\"compareFlag\":true,\"createDate\":1669198805280,\"createStaff\":21826,\"exampleValue\":\"5\",\"mustFlag\":\"F\",\"serviceObjAttrId\":912648696161382403,\"serviceObjectId\":912648696119439360,\"statusCd\":\"1000\",\"statusDate\":1669258276754,\"tenantCode\":\"868768414651416576\"},{\"attrId\":3944,\"attrSpec\":{\"attrId\":3944,\"attrName\":\"optimizeCountSql\",\"attrNbr\":\"optimizeCountSql\",\"attrValueDataType\":\"1500\",\"busiTypeId\":1,\"statusCd\":\"1000\"},\"compareFlag\":true,\"createDate\":1669198805280,\"createStaff\":21826,\"exampleValue\":\"true\",\"mustFlag\":\"F\",\"serviceObjAttrId\":912648696161382404,\"serviceObjectId\":912648696119439360,\"statusCd\":\"1000\",\"statusDate\":1669258276754,\"tenantCode\":\"868768414651416576\"},{\"attrId\":4276,\"attrSpec\":{\"attrId\":4276,\"attrName\":\"maxLimit\",\"attrNbr\":\"maxLimit\",\"attrValueDataType\":\"1200\",\"busiTypeId\":1,\"statusCd\":\"1000\"},\"compareFlag\":true,\"createDate\":1669198805280,\"createStaff\":21826,\"mustFlag\":\"F\",\"serviceObjAttrId\":912648696165576704,\"serviceObjectId\":912648696119439360,\"statusCd\":\"1000\",\"statusDate\":1669258276754,\"tenantCode\":\"868768414651416576\"},{\"attrId\":3945,\"attrSpec\":{\"attrId\":3945,\"attrName\":\"orders\",\"attrNbr\":\"orders\",\"attrValueDataType\":\"1700\",\"busiTypeId\":1,\"statusCd\":\"1000\"},\"compareFlag\":true,\"createDate\":1669198805280,\"createStaff\":21826,\"exampleValue\":\"[]\",\"mustFlag\":\"F\",\"serviceObjAttrId\":912648696165576705,\"serviceObjectId\":912648696119439360,\"statusCd\":\"1000\",\"statusDate\":1669258276754,\"tenantCode\":\"868768414651416576\"},{\"attrId\":4274,\"attrSpec\":{\"attrId\":4274,\"attrName\":\"countId\",\"attrNbr\":\"countId\",\"attrValueDataType\":\"1200\",\"busiTypeId\":1,\"statusCd\":\"1000\"},\"compareFlag\":true,\"createDate\":1669198805280,\"createStaff\":21826,\"mustFlag\":\"F\",\"serviceObjAttrId\":912648696165576706,\"serviceObjectId\":912648696119439360,\"statusCd\":\"1000\",\"statusDate\":1669258276754,\"tenantCode\":\"868768414651416576\"},{\"attrId\":3946,\"attrSpec\":{\"attrId\":3946,\"attrName\":\"isSearchCount\",\"attrNbr\":\"isSearchCount\",\"attrValueDataType\":\"1500\",\"busiTypeId\":1,\"statusCd\":\"1000\"},\"compareFlag\":true,\"createDate\":1669198805280,\"createStaff\":21826,\"exampleValue\":\"true\",\"mustFlag\":\"F\",\"serviceObjAttrId\":912648696165576707,\"serviceObjectId\":912648696119439360,\"statusCd\":\"1000\",\"statusDate\":1669258276754,\"tenantCode\":\"868768414651416576\"}],\"serviceObjectCode\":\"resultData\",\"serviceObjectId\":912648696119439360,\"serviceObjectPath\":\"912648695997804551,912648696119439360\",\"statusCd\":\"1000\",\"statusDate\":1669258276754,\"tenantCode\":\"868768414651416576\"}],\"serviceObjectAttrs\":[{\"attrId\":846210035581616128,\"attrSpec\":{\"attrId\":846210035581616128,\"attrName\":\"resultCode\",\"attrNbr\":\"resultCode\",\"attrValueDataType\":\"1200\",\"busiTypeId\":1,\"statusCd\":\"1000\"},\"compareFlag\":true,\"createDate\":1669198805280,\"createStaff\":21826,\"exampleValue\":\"0\",\"mustFlag\":\"F\",\"serviceObjAttrId\":912648696132022272,\"serviceObjectId\":912648695997804551,\"statusCd\":\"1000\",\"statusDate\":1669258276754,\"tenantCode\":\"868768414651416576\"},{\"attrId\":882598363189694465,\"attrSpec\":{\"attrId\":882598363189694465,\"attrName\":\"resultMsgCode\",\"attrNbr\":\"resultMsgCode\",\"attrValueDataType\":\"1200\",\"busiTypeId\":1,\"statusCd\":\"1000\"},\"compareFlag\":true,\"createDate\":1669198805280,\"createStaff\":21826,\"mustFlag\":\"F\",\"serviceObjAttrId\":912648696132022273,\"serviceObjectId\":912648695997804551,\"statusCd\":\"1000\",\"statusDate\":1669258276754,\"tenantCode\":\"868768414651416576\"},{\"attrId\":844138524562358274,\"attrSpec\":{\"attrId\":844138524562358274,\"attrName\":\"resultMsg\",\"attrNbr\":\"resultMsg\",\"attrValueDataType\":\"1200\",\"busiTypeId\":1,\"statusCd\":\"1000\"},\"compareFlag\":true,\"createDate\":1669198805280,\"createStaff\":21826,\"exampleValue\":\"SUCCESS\",\"mustFlag\":\"F\",\"serviceObjAttrId\":912648696132022274,\"serviceObjectId\":912648695997804551,\"statusCd\":\"1000\",\"statusDate\":1669258276754,\"tenantCode\":\"868768414651416576\"}],\"serviceObjectCode\":\"root\",\"serviceObjectId\":912648695997804551,\"serviceObjectPath\":\"912648695997804551\",\"statusCd\":\"1000\",\"statusDate\":1669258276754,\"tenantCode\":\"868768414651416576\"},\"paramObjectId\":912648695997804551,\"paramType\":\"5000\",\"statusCd\":\"1000\",\"statusDate\":1669198805280,\"tenantCode\":\"868768414651416576\"}]",
          "request": {
            "code": "root",
            "name": "根节点",
            "attrType": "object",
            "children": [
              {
                "code": "header",
                "name": "请求头参数",
                "attrType": "object"
              },
              {
                "code": "path",
                "name": "请求路径参数",
                "attrType": "object"
              },
              {
                "code": "query",
                "name": "URL 参数",
                "attrType": "object"
              },
              {
                "code": "body",
                "name": "请求体",
                "attrType": "object",
                "children": [
                  {
                    "code": "saleDesc",
                    "name": "新增节点",
                    "attrType": "field",
                    "type": "1200",
                    "mustFlag": "F",
                    "defaultValue": ""
                  },
                  {
                    "code": "saleCode",
                    "attrType": "field",
                    "type": "1200",
                    "mustFlag": "F"
                  },
                  {
                    "code": "pageSize",
                    "attrType": "field",
                    "type": "1400",
                    "mustFlag": "F"
                  },
                  {
                    "code": "pageNum",
                    "attrType": "field",
                    "type": "1400",
                    "mustFlag": "F"
                  },
                  {
                    "code": "saleName",
                    "attrType": "field",
                    "type": "1200",
                    "mustFlag": "F"
                  },
                  {
                    "code": "lanId",
                    "attrType": "field",
                    "type": "1200",
                    "mustFlag": "F"
                  },
                  {
                    "code": "saleStatus",
                    "attrType": "field",
                    "type": "1200",
                    "mustFlag": "F"
                  }
                ]
              }
            ]
          },
          "response": {
            "code": "root",
            "name": "根节点",
            "attrType": "object",
            "children": [
              {
                "code": "resultCode",
                "attrType": "field",
                "type": "1200",
                "mustFlag": "F"
              },
              {
                "code": "resultMsgCode",
                "attrType": "field",
                "type": "1200",
                "mustFlag": "F"
              },
              {
                "code": "resultMsg",
                "attrType": "field",
                "type": "1200",
                "mustFlag": "F"
              },
              {
                "code": "resultData",
                "attrType": "object",
                "children": [
                  {
                    "code": "total",
                    "attrType": "field",
                    "type": "1400",
                    "mustFlag": "F"
                  },
                  {
                    "code": "current",
                    "attrType": "field",
                    "type": "1400",
                    "mustFlag": "F"
                  },
                  {
                    "code": "hitCount",
                    "attrType": "field",
                    "type": "1500",
                    "mustFlag": "F"
                  },
                  {
                    "code": "size",
                    "attrType": "field",
                    "type": "1400",
                    "mustFlag": "F"
                  },
                  {
                    "code": "optimizeCountSql",
                    "attrType": "field",
                    "type": "1500",
                    "mustFlag": "F"
                  },
                  {
                    "code": "maxLimit",
                    "attrType": "field",
                    "type": "1200",
                    "mustFlag": "F"
                  },
                  {
                    "code": "orders",
                    "attrType": "fieldArray",
                    "mustFlag": "F",
                    "children": [
                      {
                        "code": "listItem",
                        "name": "列表元素",
                        "attrType": "field",
                        "type": "1600"
                      }
                    ]
                  },
                  {
                    "code": "countId",
                    "attrType": "field",
                    "type": "1200",
                    "mustFlag": "F"
                  },
                  {
                    "code": "isSearchCount",
                    "attrType": "field",
                    "type": "1500",
                    "mustFlag": "F"
                  },
                  {
                    "code": "records",
                    "attrType": "objectArray",
                    "children": [
                      {
                        "code": "saleCfgId",
                        "attrType": "field",
                        "type": "1400",
                        "mustFlag": "F"
                      },
                      {
                        "code": "createDate",
                        "attrType": "field",
                        "type": "1200",
                        "mustFlag": "F"
                      },
                      {
                        "code": "updateStaff",
                        "attrType": "field",
                        "type": "1200",
                        "mustFlag": "F"
                      },
                      {
                        "code": "updateDate",
                        "attrType": "field",
                        "type": "1200",
                        "mustFlag": "F"
                      },
                      {
                        "code": "saleDesc",
                        "attrType": "field",
                        "type": "1200",
                        "mustFlag": "F"
                      },
                      {
                        "code": "saleCode",
                        "attrType": "field",
                        "type": "1200",
                        "mustFlag": "F"
                      },
                      {
                        "code": "statusCd",
                        "attrType": "field",
                        "type": "1200",
                        "mustFlag": "F"
                      },
                      {
                        "code": "remark",
                        "attrType": "field",
                        "type": "1200",
                        "mustFlag": "F"
                      },
                      {
                        "code": "lanId",
                        "attrType": "field",
                        "type": "1200",
                        "mustFlag": "F"
                      },
                      {
                        "code": "saleStatus",
                        "attrType": "field",
                        "type": "1200",
                        "mustFlag": "F"
                      },
                      {
                        "code": "createStaff",
                        "attrType": "field",
                        "type": "1200",
                        "mustFlag": "F"
                      },
                      {
                        "code": "createStaffName",
                        "attrType": "field",
                        "type": "1200",
                        "mustFlag": "F"
                      },
                      {
                        "code": "saleName",
                        "attrType": "field",
                        "type": "1200",
                        "mustFlag": "F"
                      }
                    ]
                  }
                ]
              }
            ]
          },
          "productId": "912650128394563584",
          "api": "/app/rhin/gateway/callRhinEngine",
          "_source": "rhin",
          "_serviceId": "912648695968444416",
          "_serviceTitle": "根据查询条件分页查询营销案列表-tsm: qrySaleConfigPage",
          "_capabilityCode": "qrySaleConfigPage",
          "_apiCode": "qrySaleConfigPage",
          "isServiceParam": true,
          "requestType": "object",
          "responseType": "object"
        },
        "headers": []
      }
    }
  }
]
