[
  {
    "name": "nextTacheList",
    "source": "service",
    "type": "object",
    "requestType": "object",
    "filterParams": [
      {
        "attrId": "005631",
        "code": "header",
        "name": "请求头参数",
        "sort": {
          "isSort": true
        },
        "initialData": {
          "type": "static",
          "value": ""
        },
        "type": "object"
      },
      {
        "attrId": "801318",
        "code": "path",
        "name": "请求路径参数",
        "sort": {
          "isSort": true
        },
        "initialData": {
          "type": "static",
          "value": ""
        },
        "type": "object"
      },
      {
        "attrId": "235973",
        "code": "query",
        "name": "URL 参数",
        "sort": {
          "isSort": true
        },
        "initialData": {
          "type": "static",
          "value": ""
        },
        "type": "object"
      },
      {
        "attrId": "628615",
        "code": "body",
        "name": "请求体",
        "sort": {
          "isSort": true
        },
        "initialData": {
          "type": "static",
          "value": ""
        },
        "type": "object",
        "children": [
          {
            "attrId": "373283",
            "code": "tachePass",
            "name": "审批结果",
            "sort": {
              "isSort": true
            },
            "initialData": {
              "type": "static"
            },
            "type": "string"
          },
          {
            "attrId": "951065",
            "code": "orderType",
            "name": "流程订单类型",
            "sort": {
              "isSort": true
            },
            "initialData": {
              "type": "static"
            },
            "type": "string"
          },
          {
            "attrId": "130326",
            "code": "endLevel",
            "name": "最高审批等级",
            "sort": {
              "isSort": true
            },
            "initialData": {
              "type": "static"
            },
            "type": "string"
          },
          {
            "attrId": "100482",
            "code": "tacheCode",
            "name": "环节编码",
            "sort": {
              "isSort": true
            },
            "initialData": {
              "type": "static"
            },
            "type": "string"
          },
          {
            "attrId": "174732",
            "code": "flowCode",
            "name": "流程编码",
            "sort": {
              "isSort": true
            },
            "initialData": {
              "type": "static"
            },
            "type": "string"
          },
          {
            "attrId": "167252",
            "code": "workId",
            "name": "流程实例id",
            "sort": {
              "isSort": true
            },
            "initialData": {
              "type": "static"
            },
            "type": "string"
          },
          {
            "attrId": "777996",
            "code": "workItemId",
            "name": "流程环节实例id",
            "sort": {
              "isSort": true
            },
            "initialData": {
              "type": "static"
            },
            "type": "string"
          }
        ]
      }
    ],
    "outParams": [
      {
        "attrId": "348994",
        "code": "resultMsgCode",
        "name": "resultMsgCode",
        "sort": {
          "isSort": true
        },
        "initialData": {
          "type": "static"
        },
        "type": "string"
      },
      {
        "attrId": "961445",
        "code": "resultMsg",
        "name": "resultMsg",
        "sort": {
          "isSort": true
        },
        "initialData": {
          "type": "static"
        },
        "type": "string"
      },
      {
        "attrId": "725231",
        "code": "resultCode",
        "name": "resultCode",
        "sort": {
          "isSort": true
        },
        "initialData": {
          "type": "static"
        },
        "type": "string"
      },
      {
        "attrId": "972205",
        "code": "resultData",
        "name": "resultData",
        "sort": {
          "isSort": true
        },
        "initialData": {
          "type": "static"
        },
        "type": "objectArray",
        "children": [
          {
            "attrId": "927784",
            "code": "tacheName",
            "name": "环节名称",
            "sort": {
              "isSort": true
            },
            "initialData": {
              "type": "static"
            },
            "type": "string"
          },
          {
            "attrId": "7057",
            "code": "tacheCode",
            "name": "环节编码",
            "sort": {
              "isSort": true
            },
            "initialData": {
              "type": "static"
            },
            "type": "string"
          },
          {
            "attrId": "704419",
            "code": "fixedUser",
            "name": "新增节点",
            "sort": {
              "isSort": true
            },
            "initialData": {
              "type": "static"
            },
            "type": "string"
          },
          {
            "attrId": "783881",
            "code": "hideUserSelect",
            "name": "新增节点",
            "sort": {
              "isSort": true
            },
            "initialData": {
              "type": "static"
            },
            "type": "string"
          },
          {
            "attrId": "157896",
            "code": "popupType",
            "name": "选人弹窗类型",
            "sort": {
              "isSort": true
            },
            "initialData": {
              "type": "static"
            },
            "type": "string"
          }
        ]
      }
    ],
    "config": {
      "hooks": [],
      "isInit": false,
      "options": {
        "service": {
          "busiApiId": "874463664148983808",
          "busiApiNbr": "queryNextTacheList",
          "busiApiName": "获取下一环节信息-tzp",
          "busiObjId": "874463664148983808",
          "apiParam": "[{\"apiId\":874463664148983808,\"apiParamId\":874463664195121152,\"compareFlag\":true,\"createDate\":1660094783922,\"createStaff\":50171,\"objId\":874463664148983808,\"objType\":\"5000\",\"paramObject\":{\"compareFlag\":true,\"createDate\":1660094783922,\"createStaff\":50171,\"isList\":\"F\",\"level\":1,\"parServiceObjectId\":-1,\"paramType\":\"1000\",\"remark\":\"根节点，这个节点不能删除\",\"rootServiceObjectId\":874463664199315456,\"serviceObject\":[],\"serviceObjectCode\":\"root\",\"serviceObjectId\":874463664199315456,\"serviceObjectPath\":\"874463664199315456\",\"statusCd\":\"1000\",\"statusDate\":1665972036229,\"tenantCode\":\"868768414651416576\"},\"paramObjectId\":874463664199315456,\"paramType\":\"1000\",\"statusCd\":\"1000\",\"statusDate\":1660094783922,\"tenantCode\":\"868768414651416576\"},{\"apiId\":874463664148983808,\"apiParamId\":874463664203509760,\"compareFlag\":true,\"createDate\":1660094783922,\"createStaff\":50171,\"objId\":874463664148983808,\"objType\":\"5000\",\"paramObject\":{\"compareFlag\":true,\"createDate\":1660094783922,\"createStaff\":50171,\"isList\":\"F\",\"level\":1,\"parServiceObjectId\":-1,\"paramType\":\"2000\",\"remark\":\"根节点，这个节点不能删除\",\"rootServiceObjectId\":874463664203509761,\"serviceObject\":[],\"serviceObjectCode\":\"root\",\"serviceObjectId\":874463664203509761,\"serviceObjectPath\":\"874463664203509761\",\"statusCd\":\"1000\",\"statusDate\":1665972036229,\"tenantCode\":\"868768414651416576\"},\"paramObjectId\":874463664203509761,\"paramType\":\"2000\",\"statusCd\":\"1000\",\"statusDate\":1660094783922,\"tenantCode\":\"868768414651416576\"},{\"apiId\":874463664148983808,\"apiParamId\":874463664203509762,\"compareFlag\":true,\"createDate\":1660094783922,\"createStaff\":50171,\"objId\":874463664148983808,\"objType\":\"5000\",\"paramObject\":{\"compareFlag\":true,\"createDate\":1660094783922,\"createStaff\":50171,\"isList\":\"F\",\"level\":1,\"parServiceObjectId\":-1,\"paramType\":\"3000\",\"remark\":\"根节点，这个节点不能删除\",\"rootServiceObjectId\":874463664203509763,\"serviceObject\":[],\"serviceObjectCode\":\"root\",\"serviceObjectId\":874463664203509763,\"serviceObjectPath\":\"874463664203509763\",\"statusCd\":\"1000\",\"statusDate\":1665972036229,\"tenantCode\":\"868768414651416576\"},\"paramObjectId\":874463664203509763,\"paramType\":\"3000\",\"statusCd\":\"1000\",\"statusDate\":1660094783922,\"tenantCode\":\"868768414651416576\"},{\"apiId\":874463664148983808,\"apiParamId\":874463664203509764,\"compareFlag\":true,\"createDate\":1660094783922,\"createStaff\":50171,\"objId\":874463664148983808,\"objType\":\"5000\",\"paramObject\":{\"compareFlag\":true,\"createDate\":1660094783922,\"createStaff\":50171,\"isList\":\"F\",\"level\":1,\"parServiceObjectId\":-1,\"paramType\":\"4000\",\"remark\":\"根节点\",\"rootServiceObjectId\":874463664203509765,\"serviceObject\":[],\"serviceObjectAttrs\":[{\"attrId\":874581938635124738,\"attrSpec\":{\"attrId\":874581938635124738,\"attrName\":\"tachePass\",\"attrNbr\":\"tachePass\",\"attrValueDataType\":\"1200\",\"busiTypeId\":1,\"statusCd\":\"1000\"},\"compareFlag\":true,\"createDate\":1660122982729,\"createStaff\":50171,\"exampleValue\":\"refuse\",\"mustFlag\":\"F\",\"remark\":\"审批结果\",\"serviceObjAttrId\":874581938635124737,\"serviceObjectId\":874463664203509765,\"statusCd\":\"1000\",\"statusDate\":1665972036229,\"tenantCode\":\"868768414651416576\"},{\"attrId\":1232,\"attrSpec\":{\"attrId\":1232,\"attrName\":\"orderType\",\"attrNbr\":\"orderType\",\"attrValueDataType\":\"1200\",\"busiTypeId\":1,\"statusCd\":\"1000\"},\"compareFlag\":true,\"createDate\":1660122982729,\"createStaff\":50171,\"exampleValue\":\"1100\",\"mustFlag\":\"F\",\"remark\":\"流程订单类型\",\"serviceObjAttrId\":874581938635124739,\"serviceObjectId\":874463664203509765,\"statusCd\":\"1000\",\"statusDate\":1665972036229,\"tenantCode\":\"868768414651416576\"},{\"attrId\":878105725102628867,\"attrSpec\":{\"attrId\":878105725102628867,\"attrName\":\"最高审批等级\",\"attrNbr\":\"endLevel\",\"attrValueDataType\":\"1200\",\"busiTypeId\":1,\"statusCd\":\"1000\"},\"compareFlag\":true,\"createDate\":1660976027557,\"createStaff\":50171,\"defaultValue\":\"\",\"desensitizeRule\":\"1001\",\"desensitizeType\":\"1001\",\"exampleValue\":\"\",\"mustFlag\":\"F\",\"remark\":\"最高审批等级\",\"serviceObjAttrId\":878159867870187520,\"serviceObjectId\":874463664203509765,\"statusCd\":\"1000\",\"statusDate\":1665972036229,\"tenantCode\":\"868768414651416576\"},{\"attrId\":873874531156643841,\"attrSpec\":{\"attrId\":873874531156643841,\"attrName\":\"tacheCode\",\"attrNbr\":\"tacheCode\",\"attrValueDataType\":\"1200\",\"busiTypeId\":1,\"statusCd\":\"1000\"},\"compareFlag\":true,\"createDate\":1660122982729,\"createStaff\":50171,\"exampleValue\":\"bzz-audit\",\"mustFlag\":\"F\",\"remark\":\"环节编码\",\"serviceObjAttrId\":874581938635124736,\"serviceObjectId\":874463664203509765,\"statusCd\":\"1000\",\"statusDate\":1665972036229,\"tenantCode\":\"868768414651416576\"},{\"attrId\":4340,\"attrSpec\":{\"attrId\":4340,\"attrName\":\"flowCode\",\"attrNbr\":\"flowCode\",\"attrValueDataType\":\"1200\",\"busiTypeId\":1,\"statusCd\":\"1000\"},\"compareFlag\":true,\"createDate\":1661136104008,\"createStaff\":50171,\"defaultValue\":\"\",\"desensitizeRule\":\"1001\",\"desensitizeType\":\"1001\",\"exampleValue\":\"\",\"mustFlag\":\"F\",\"remark\":\"流程编码\",\"serviceObjAttrId\":878831276598272000,\"serviceObjectId\":874463664203509765,\"statusCd\":\"1000\",\"statusDate\":1665972036229,\"tenantCode\":\"868768414651416576\"},{\"attrId\":4371,\"attrSpec\":{\"attrId\":4371,\"attrName\":\"workId\",\"attrNbr\":\"workId\",\"attrValueDataType\":\"1200\",\"busiTypeId\":1,\"statusCd\":\"1000\"},\"compareFlag\":true,\"createDate\":1662040570190,\"createStaff\":50171,\"exampleValue\":\"6601\",\"mustFlag\":\"F\",\"remark\":\"流程实例id\",\"serviceObjAttrId\":882624882965622784,\"serviceObjectId\":874463664203509765,\"statusCd\":\"1000\",\"statusDate\":1665972036229,\"tenantCode\":\"868768414651416576\"},{\"attrId\":873869939408785408,\"attrSpec\":{\"attrId\":873869939408785408,\"attrName\":\"workItemId\",\"attrNbr\":\"workItemId\",\"attrValueDataType\":\"1200\",\"busiTypeId\":1,\"statusCd\":\"1000\"},\"compareFlag\":true,\"createDate\":1660904333053,\"createStaff\":50171,\"defaultValue\":\"\",\"desensitizeRule\":\"1001\",\"desensitizeType\":\"1001\",\"exampleValue\":\"\",\"mustFlag\":\"F\",\"remark\":\"流程环节实例id\",\"serviceObjAttrId\":877859159143596032,\"serviceObjectId\":874463664203509765,\"statusCd\":\"1000\",\"statusDate\":1665972036229,\"tenantCode\":\"868768414651416576\"}],\"serviceObjectCode\":\"root\",\"serviceObjectId\":874463664203509765,\"serviceObjectPath\":\"874463664203509765\",\"statusCd\":\"1000\",\"statusDate\":1665972036229,\"tenantCode\":\"868768414651416576\"},\"paramObjectId\":874463664203509765,\"paramType\":\"4000\",\"statusCd\":\"1000\",\"statusDate\":1660094783922,\"tenantCode\":\"868768414651416576\"},{\"apiId\":874463664148983808,\"apiParamId\":874463664203509766,\"compareFlag\":true,\"createDate\":1660094783922,\"createStaff\":50171,\"objId\":874463664148983808,\"objType\":\"5000\",\"paramObject\":{\"compareFlag\":true,\"createDate\":1660094783922,\"createStaff\":50171,\"isList\":\"F\",\"level\":1,\"parServiceObjectId\":-1,\"paramType\":\"5000\",\"remark\":\"根节点\",\"rootServiceObjectId\":874463664207704064,\"serviceObject\":[{\"compareFlag\":true,\"createDate\":1660094783922,\"createStaff\":50171,\"isList\":\"T\",\"level\":2,\"parServiceObjectId\":874463664207704064,\"paramType\":\"5000\",\"rootServiceObjectId\":874463664207704064,\"serviceObject\":[],\"serviceObjectAttrs\":[{\"attrId\":874463664614551554,\"attrSpec\":{\"attrId\":874463664614551554,\"attrName\":\"tacheName\",\"attrNbr\":\"tacheName\",\"attrValueDataType\":\"1200\",\"busiTypeId\":1,\"statusCd\":\"1000\"},\"compareFlag\":true,\"createDate\":1660094783922,\"createStaff\":50171,\"exampleValue\":\"业管/项目经理\",\"mustFlag\":\"F\",\"remark\":\"环节名称\",\"serviceObjAttrId\":874463664614551553,\"serviceObjectId\":874463664568414208,\"statusCd\":\"1000\",\"statusDate\":1665972036229,\"tenantCode\":\"868768414651416576\"},{\"attrId\":873874531156643841,\"attrSpec\":{\"attrId\":873874531156643841,\"attrName\":\"tacheCode\",\"attrNbr\":\"tacheCode\",\"attrValueDataType\":\"1200\",\"busiTypeId\":1,\"statusCd\":\"1000\"},\"compareFlag\":true,\"createDate\":1660094783922,\"createStaff\":50171,\"exampleValue\":\"ygxmjl-audit\",\"mustFlag\":\"F\",\"remark\":\"环节编码\",\"serviceObjAttrId\":874463664614551552,\"serviceObjectId\":874463664568414208,\"statusCd\":\"1000\",\"statusDate\":1665972036229,\"tenantCode\":\"868768414651416576\"},{\"attrId\":884018713568313345,\"attrSpec\":{\"attrId\":884018713568313345,\"attrName\":\"fixedUser\",\"attrNbr\":\"fixedUser\",\"attrValueDataType\":\"1200\",\"busiTypeId\":1,\"statusCd\":\"1000\"},\"compareFlag\":true,\"createDate\":1662372885275,\"createStaff\":50171,\"defaultValue\":\"\",\"desensitizeRule\":\"1001\",\"desensitizeType\":\"1001\",\"exampleValue\":\"\",\"mustFlag\":\"F\",\"remark\":\"新增节点\",\"serviceObjAttrId\":884018713568313344,\"serviceObjectId\":874463664568414208,\"statusCd\":\"1000\",\"statusDate\":1665972036229,\"tenantCode\":\"868768414651416576\"},{\"attrId\":878932412969553921,\"attrSpec\":{\"attrId\":878932412969553921,\"attrName\":\"hideUserSelect\",\"attrNbr\":\"hideUserSelect\",\"attrValueDataType\":\"1200\",\"busiTypeId\":1,\"statusCd\":\"1000\"},\"compareFlag\":true,\"createDate\":1665972036229,\"createStaff\":50171,\"defaultValue\":\"\",\"desensitizeRule\":\"1001\",\"desensitizeType\":\"1001\",\"exampleValue\":\"\",\"mustFlag\":\"F\",\"remark\":\"新增节点\",\"serviceObjAttrId\":899114647323119616,\"serviceObjectId\":874463664568414208,\"statusCd\":\"1000\",\"statusDate\":1665972036229,\"tenantCode\":\"868768414651416576\"},{\"attrId\":899114647327313920,\"attrSpec\":{\"attrId\":899114647327313920,\"attrName\":\"选人弹窗类型\",\"attrNbr\":\"popupType\",\"attrValueDataType\":\"1200\",\"busiTypeId\":1,\"statusCd\":\"1000\"},\"compareFlag\":true,\"createDate\":1665972036229,\"createStaff\":50171,\"defaultValue\":\"\",\"desensitizeRule\":\"1001\",\"desensitizeType\":\"1001\",\"exampleValue\":\"\",\"mustFlag\":\"F\",\"remark\":\"选人弹窗类型\",\"serviceObjAttrId\":899114647323119617,\"serviceObjectId\":874463664568414208,\"statusCd\":\"1000\",\"statusDate\":1665972036229,\"tenantCode\":\"868768414651416576\"}],\"serviceObjectCode\":\"resultData\",\"serviceObjectId\":874463664568414208,\"serviceObjectPath\":\"874463664207704064,874463664568414208\",\"statusCd\":\"1000\",\"statusDate\":1665972036229,\"tenantCode\":\"868768414651416576\"}],\"serviceObjectAttrs\":[{\"attrId\":874132034551685121,\"attrSpec\":{\"attrId\":874132034551685121,\"attrName\":\"resultMsgCode\",\"attrNbr\":\"resultMsgCode\",\"attrValueDataType\":\"1200\",\"busiTypeId\":1,\"statusCd\":\"1000\"},\"compareFlag\":true,\"createDate\":1660094783922,\"createStaff\":50171,\"mustFlag\":\"F\",\"serviceObjAttrId\":874463664585191424,\"serviceObjectId\":874463664207704064,\"statusCd\":\"1000\",\"statusDate\":1665972036229,\"tenantCode\":\"868768414651416576\"},{\"attrId\":842306878819315714,\"attrSpec\":{\"attrId\":842306878819315714,\"attrName\":\"resultMsg\",\"attrNbr\":\"resultMsg\",\"attrValueDataType\":\"1200\",\"busiTypeId\":1,\"statusCd\":\"1000\"},\"compareFlag\":true,\"createDate\":1662372885275,\"createStaff\":50171,\"exampleValue\":\"SUCCESS\",\"mustFlag\":\"F\",\"serviceObjAttrId\":884018713731891200,\"serviceObjectId\":874463664207704064,\"statusCd\":\"1000\",\"statusDate\":1665972036229,\"tenantCode\":\"868768414651416576\"},{\"attrId\":1226,\"attrSpec\":{\"attrId\":1226,\"attrName\":\"resultCode\",\"attrNbr\":\"resultCode\",\"attrValueDataType\":\"1200\",\"busiTypeId\":1,\"statusCd\":\"1000\"},\"compareFlag\":true,\"createDate\":1665972036229,\"createStaff\":50171,\"exampleValue\":\"0\",\"mustFlag\":\"F\",\"serviceObjAttrId\":899114647495086080,\"serviceObjectId\":874463664207704064,\"statusCd\":\"1000\",\"statusDate\":1665972036229,\"tenantCode\":\"868768414651416576\"}],\"serviceObjectCode\":\"root\",\"serviceObjectId\":874463664207704064,\"serviceObjectPath\":\"874463664207704064\",\"statusCd\":\"1000\",\"statusDate\":1665972036229,\"tenantCode\":\"868768414651416576\"},\"paramObjectId\":874463664207704064,\"paramType\":\"5000\",\"statusCd\":\"1000\",\"statusDate\":1660094783922,\"tenantCode\":\"868768414651416576\"}]",
          "request": {
            "code": "root",
            "name": "根节点",
            "attrType": "object",
            "children": [
              {
                "code": "header",
                "name": "请求头参数",
                "attrType": "object",
                "_id": "header",
                "compType": "Input"
              },
              {
                "code": "path",
                "name": "请求路径参数",
                "attrType": "object",
                "_id": "path",
                "compType": "Input"
              },
              {
                "code": "query",
                "name": "URL 参数",
                "attrType": "object",
                "_id": "query",
                "compType": "Input"
              },
              {
                "code": "body",
                "name": "请求体",
                "attrType": "object",
                "children": [
                  {
                    "code": "tachePass",
                    "name": "审批结果",
                    "attrType": "field",
                    "type": "string",
                    "mustFlag": "F",
                    "_id": "body.tachePass",
                    "compType": "Input"
                  },
                  {
                    "code": "orderType",
                    "name": "流程订单类型",
                    "attrType": "field",
                    "type": "string",
                    "mustFlag": "F",
                    "_id": "body.orderType",
                    "compType": "Input"
                  },
                  {
                    "code": "endLevel",
                    "name": "最高审批等级",
                    "attrType": "field",
                    "type": "string",
                    "mustFlag": "F",
                    "defaultValue": "",
                    "_id": "body.endLevel",
                    "compType": "Input"
                  },
                  {
                    "code": "tacheCode",
                    "name": "环节编码",
                    "attrType": "field",
                    "type": "string",
                    "mustFlag": "F",
                    "_id": "body.tacheCode",
                    "compType": "Input"
                  },
                  {
                    "code": "flowCode",
                    "name": "流程编码",
                    "attrType": "field",
                    "type": "string",
                    "mustFlag": "F",
                    "defaultValue": "",
                    "_id": "body.flowCode",
                    "compType": "Input"
                  },
                  {
                    "code": "workId",
                    "name": "流程实例id",
                    "attrType": "field",
                    "type": "string",
                    "mustFlag": "F",
                    "_id": "body.workId",
                    "compType": "Input"
                  },
                  {
                    "code": "workItemId",
                    "name": "流程环节实例id",
                    "attrType": "field",
                    "type": "string",
                    "mustFlag": "F",
                    "defaultValue": "",
                    "_id": "body.workItemId",
                    "compType": "Input"
                  }
                ],
                "_id": "body",
                "compType": "Input"
              }
            ]
          },
          "response": {
            "code": "root",
            "name": "根节点",
            "attrType": "object",
            "children": [
              {
                "code": "resultMsgCode",
                "attrType": "field",
                "type": "string",
                "mustFlag": "F",
                "_id": "resultMsgCode",
                "name": "resultMsgCode"
              },
              {
                "code": "resultMsg",
                "attrType": "field",
                "type": "string",
                "mustFlag": "F",
                "_id": "resultMsg",
                "name": "resultMsg"
              },
              {
                "code": "resultCode",
                "attrType": "field",
                "type": "string",
                "mustFlag": "F",
                "_id": "resultCode",
                "name": "resultCode"
              },
              {
                "code": "resultData",
                "attrType": "objectArray",
                "children": [
                  {
                    "code": "tacheName",
                    "name": "环节名称",
                    "attrType": "field",
                    "type": "string",
                    "mustFlag": "F",
                    "_id": "resultData.tacheName"
                  },
                  {
                    "code": "tacheCode",
                    "name": "环节编码",
                    "attrType": "field",
                    "type": "string",
                    "mustFlag": "F",
                    "_id": "resultData.tacheCode"
                  },
                  {
                    "code": "fixedUser",
                    "name": "新增节点",
                    "attrType": "field",
                    "type": "string",
                    "mustFlag": "F",
                    "defaultValue": "",
                    "_id": "resultData.fixedUser"
                  },
                  {
                    "code": "hideUserSelect",
                    "name": "新增节点",
                    "attrType": "field",
                    "type": "string",
                    "mustFlag": "F",
                    "defaultValue": "",
                    "_id": "resultData.hideUserSelect"
                  },
                  {
                    "code": "popupType",
                    "name": "选人弹窗类型",
                    "attrType": "field",
                    "type": "string",
                    "mustFlag": "F",
                    "defaultValue": "",
                    "_id": "resultData.popupType"
                  }
                ],
                "_id": "resultData",
                "name": "resultData"
              }
            ]
          },
          "isServiceParam": true,
          "productId": "11027",
          "api": "/app/rhin/gateway/callRhinEngine",
          "_source": "rhin",
          "_serviceId": "874463664148983808",
          "_serviceTitle": "获取下一环节信息-tzp: queryNextTacheList",
          "_capabilityCode": "queryNextTacheList",
          "_apiCode": "queryNextTacheList",
          "requestType": "object",
          "responseType": "object"
        },
        "headers": []
      }
    }
  },
  {
    "name": "globalParam",
    "source": "custom",
    "type": "object",
    "outParams": [
      {
        "attrId": "8768114",
        "code": "flowCode",
        "name": "属性",
        "type": "string",
        "initialData": {
          "type": "static",
          "value": "流程编码"
        }
      },
      {
        "attrId": "419751",
        "code": "popupType",
        "name": "属性",
        "type": "string",
        "initialData": {
          "type": "static",
          "value": "处理人弹出框类型"
        }
      },
      {
        "attrId": "001699",
        "code": "workItemId",
        "name": "属性",
        "type": "string",
        "initialData": {
          "type": "static",
          "value": "流程环节实例id"
        }
      }
    ]
  }
]
